autocron/__init__.py
autocron/cli.py
autocron/logger.py
autocron/notifications.py
autocron/os_adapters.py
autocron/py.typed
autocron/scheduler.py
autocron/utils.py
autocron/version.py
autocron_scheduler-1.0.1.dist-info/licenses/LICENSE
autocron_scheduler-1.0.1.dist-info/METADATA
autocron_scheduler-1.0.1.dist-info/WHEEL
autocron_scheduler-1.0.1.dist-info/entry_points.txt
autocron_scheduler-1.0.1.dist-info/top_level.txt
autocron_scheduler-1.0.1.dist-info/RECORD
