Metadata-Version: 2.4
Name: autocron-scheduler
Version: 1.0.1
Summary: Automate scripts with zero setup. Run Python tasks anytime, anywhere.
Author-email: MD Shoaib Uddin Chanda <mdshoaibuddinchanda@gmail.com>
Maintainer-email: MD Shoaib Uddin Chanda <mdshoaibuddinchanda@gmail.com>
License: MIT
Project-URL: Homepage, https://github.com/mdshoaibuddinchanda/autocron
Project-URL: Documentation, https://autocron.readthedocs.io
Project-URL: Repository, https://github.com/mdshoaibuddinchanda/autocron
Project-URL: Bug Tracker, https://github.com/mdshoaibuddinchanda/autocron/issues
Keywords: scheduler,cron,automation,task,periodic,cross-platform
Classifier: Development Status :: 5 - Production/Stable
Classifier: Intended Audience :: Developers
Classifier: License :: OSI Approved :: MIT License
Classifier: Programming Language :: Python :: 3
Classifier: Programming Language :: Python :: 3.10
Classifier: Programming Language :: Python :: 3.11
Classifier: Programming Language :: Python :: 3.12
Classifier: Programming Language :: Python :: 3.13
Classifier: Programming Language :: Python :: 3.14
Classifier: Operating System :: OS Independent
Classifier: Operating System :: Microsoft :: Windows
Classifier: Operating System :: POSIX :: Linux
Classifier: Operating System :: MacOS
Classifier: Topic :: Software Development :: Libraries :: Python Modules
Classifier: Topic :: System :: Monitoring
Classifier: Topic :: Utilities
Requires-Python: >=3.10
License-File: LICENSE
Requires-Dist: croniter>=1.4.0
Requires-Dist: python-crontab>=3.0.0; platform_system == "Linux" or platform_system == "Darwin"
Requires-Dist: pywin32>=305; platform_system == "Windows"
Requires-Dist: tqdm>=4.66.5
Requires-Dist: psutil>=5.9.0
Requires-Dist: pyyaml>=6.0
Provides-Extra: dev
Requires-Dist: pytest>=7.4.0; extra == "dev"
Requires-Dist: pytest-cov>=4.1.0; extra == "dev"
Requires-Dist: pytest-mock>=3.11.0; extra == "dev"
Requires-Dist: pytest-timeout>=2.1.0; extra == "dev"
Requires-Dist: black>=24.8.0; extra == "dev"
Requires-Dist: flake8>=6.1.0; extra == "dev"
Requires-Dist: mypy>=1.5.0; extra == "dev"
Requires-Dist: isort>=5.12.0; extra == "dev"
Requires-Dist: pylint>=2.17.0; extra == "dev"
Provides-Extra: notifications
Requires-Dist: plyer>=2.1.0; extra == "notifications"
Dynamic: license-file
